[
    {
        "id": 1,
        "username": "user",
        "nom": "Fradi",
        "prenom": "Oussama",
        "password": null,
        "profession": "developpeur",
        "enable": true,
        "roles": [
            {
                "id": 1,
                "name": "ROLE_USER"
            }
        ]
    },
    {
        "id": 2,
        "username": "admin",
        "nom": "Fradi",
        "prenom": "Oussama",
        "password": null,
        "profession": "developpeur",
        "enable": true,
        "roles": [
            {
                "id": 1,
                "name": "ROLE_USER"
            },
            {
                "id": 2,
                "name": "ROLE_ADMIN"
            }
        ]
    }
]